countess_minimap2.py
countess_minimap2-0.0.14.dist-info/LICENSE.txt
countess_minimap2-0.0.14.dist-info/METADATA
countess_minimap2-0.0.14.dist-info/WHEEL
countess_minimap2-0.0.14.dist-info/entry_points.txt
countess_minimap2-0.0.14.dist-info/top_level.txt
countess_minimap2-0.0.14.dist-info/RECORD
