Metadata-Version: 2.1
Name: countess-minimap2
Version: 0.0.14
Summary: Sequence Alignment Plugin for CountESS, based in Minimap2
Author-email: Nick Moore <nick@zoic.org>
Maintainer-email: Nick Moore <nick@zoic.org>
License: BSD-3-Clause
Project-URL: Homepage, https://github.com/CountESS-Project/countess-minimap2
Project-URL: Repository, https://github.com/CountESS-Project/countess-minimap2.git
Classifier: Development Status :: 2 - Pre-Alpha
Classifier: Intended Audience :: Science/Research
Classifier: License :: OSI Approved :: BSD License
Classifier: Operating System :: OS Independent
Classifier: Topic :: Scientific/Engineering :: Bio-Informatics
Requires-Python: >=3.10
License-File: LICENSE.txt
Requires-Dist: countess>=0.0.67
Requires-Dist: mappy~=2.26
Provides-Extra: dev
Requires-Dist: countess[dev]>=0.0.67; extra == "dev"
